functional_pipeline/__init__.py
functional_pipeline/pipeline.py
functional_pipeline/helpers/__init__.py
functional_pipeline/helpers/curry.py
functional_pipeline/helpers/string_helper.py
functional_pipeline/helpers/utils.py
functional_pipeline-0.6.1.dist-info/LICENSE
functional_pipeline-0.6.1.dist-info/METADATA
functional_pipeline-0.6.1.dist-info/WHEEL
functional_pipeline-0.6.1.dist-info/top_level.txt
functional_pipeline-0.6.1.dist-info/RECORD
