Metadata-Version: 2.1
Name: functional-pipeline
Version: 0.6.1
Summary: Functional Pipelines implemented in python
Home-page: https://gitlab.com/mc706/functional-pipeline
Author: Ryan McDevitt
Author-email: mcdevitt.ryan@gmail.com
License: UNKNOWN
Project-URL: Docs, https://functional-pipeline.readthedocs.io/en/stable/#
Project-URL: Source, https://gitlab.com/mc706/functional-pipeline
Project-URL: Bug Reports/Issues, https://gitlab.com/mc706/functional-pipeline/issues
Platform: UNKNOWN
Classifier: Development Status :: 4 - Beta
Classifier: Intended Audience :: Developers
Classifier: License :: OSI Approved :: MIT License
Classifier: Programming Language :: Python :: 3.6
Classifier: Programming Language :: Python :: 3.7
Classifier: Programming Language :: Python :: 3.8
Classifier: Programming Language :: Python :: 3.9
Classifier: Topic :: Software Development :: Libraries
Classifier: Topic :: Utilities
Provides-Extra: dev
Requires-Dist: prospector ; extra == 'dev'
Requires-Dist: coverage ; extra == 'dev'
Requires-Dist: mypy ; extra == 'dev'
Requires-Dist: pytest ; extra == 'dev'
Requires-Dist: pytest-cov ; extra == 'dev'
